alphapy/__init__.py
alphapy/alias.py
alphapy/alphapy_main.py
alphapy/calendrical.py
alphapy/data.py
alphapy/estimators.py
alphapy/features.py
alphapy/frame.py
alphapy/globals.py
alphapy/group.py
alphapy/metalabel.py
alphapy/mflow_main.py
alphapy/model.py
alphapy/nlp.py
alphapy/optimize.py
alphapy/plots.py
alphapy/portfolio.py
alphapy/space.py
alphapy/system.py
alphapy/transforms.py
alphapy/utilities.py
alphapy/variables.py
alphapy_pro-3.0.0.dist-info/METADATA
alphapy_pro-3.0.0.dist-info/WHEEL
alphapy_pro-3.0.0.dist-info/entry_points.txt
alphapy_pro-3.0.0.dist-info/licenses/LICENSE
alphapy_pro-3.0.0.dist-info/RECORD
