Metadata-Version: 2.4
Name: alphapy-pro
Version: 3.0.0
Summary: AlphaPy Pro: A Machine Learning Pipeline for Speculators
Project-URL: Homepage, https://github.com/ScottFreeLLC/alphapy-pro
Project-URL: Documentation, https://scottfreellc.github.io/alphapy-pro/
Project-URL: Repository, https://github.com/ScottFreeLLC/alphapy-pro.git
Project-URL: Bug Tracker, https://github.com/ScottFreeLLC/alphapy-pro/issues
Author-email: "Robert D. Scott II" <scottfree.analytics@scottfreellc.com>, Mark Conway <scottfree.analytics@scottfreellc.com>
Maintainer-email: ScottFree LLC <scottfree.analytics@scottfreellc.com>
License-Expression: Apache-2.0
License-File: LICENSE
Keywords: finance,machine learning,pandas,prediction,scikit-learn,sports,trading
Classifier: Development Status :: 4 - Beta
Classifier: Intended Audience :: Science/Research
Classifier: Operating System :: OS Independent
Classifier: Programming Language :: Python
Classifier: Programming Language :: Python :: 3
Classifier: Programming Language :: Python :: 3.12
Classifier: Topic :: Scientific/Engineering
Classifier: Topic :: Scientific/Engineering :: Mathematics
Requires-Python: >=3.12
Requires-Dist: arrow>=0.13
Requires-Dist: bokeh>=1.3
Requires-Dist: category-encoders>=2.1
Requires-Dist: iexfinance>=0.4.3
Requires-Dist: imbalanced-learn>=0.5
Requires-Dist: ipython>=7.2
Requires-Dist: lofo-importance>=0.3.4
Requires-Dist: matplotlib>=3.0
Requires-Dist: numpy>=1.20
Requires-Dist: pandas-datareader>=0.10.0
Requires-Dist: pandas>=1.3
Requires-Dist: polygon-api-client>=1.13.4
Requires-Dist: pyyaml>=5.0
Requires-Dist: scikit-learn>=1.0
Requires-Dist: scipy<1.14,>=1.7
Requires-Dist: seaborn>=0.11
Requires-Dist: setuptools>=61.0
Requires-Dist: statsmodels<0.15.0,>=0.13.0
Requires-Dist: venn-abers>=1.4.1
Requires-Dist: xgboost>=3.0.4
Requires-Dist: yfinance>=0.1.59
Provides-Extra: dev
Requires-Dist: black>=22.0; extra == 'dev'
Requires-Dist: build>=0.8; extra == 'dev'
Requires-Dist: flake8>=4.0; extra == 'dev'
Requires-Dist: isort>=5.0; extra == 'dev'
Requires-Dist: pre-commit>=2.0; extra == 'dev'
Requires-Dist: pytest-cov>=2.0; extra == 'dev'
Requires-Dist: pytest>=6.0; extra == 'dev'
Requires-Dist: twine>=4.0; extra == 'dev'
Provides-Extra: docs
Requires-Dist: sphinx-rtd-dark-mode>=1.0; extra == 'docs'
Requires-Dist: sphinx-rtd-theme>=1.0; extra == 'docs'
Requires-Dist: sphinx>=4.0; extra == 'docs'
Provides-Extra: test
Requires-Dist: pytest-cov>=2.0; extra == 'test'
Requires-Dist: pytest-xdist>=2.0; extra == 'test'
Requires-Dist: pytest>=6.0; extra == 'test'
